{"page":"John Carroll Andy Mathay","page_id":"75775430","share_type":"discussion","created":"2007-10-25T09:45:52-07:00","createdBy":"support","title":"Zach Noyes : question about your teams affs","description":"Hi. I am Zach Noyes, a debater for the University of Rochester. I am going to Clarion this Weekend. What aff's do these two teams run: <br \/>\n<br \/>\nJohn Carroll Univers    Jane Killian &amp; Anthony Miranda    JV Policy<br \/>\nJohn Carroll Univers    Brian Brossmann &amp; Rachel Cope    JV Policy<br \/>\n<br \/>\nAre they the same as this one? Thank you.<br \/>\nyou can reply @ <!-- ws:start:WikiTextUrlEmailRule:7:znoyes@gmail.com --><a class=\"wiki_link_ext\" href=\"mailto:znoyes@gmail.com\" rel=\"nofollow\">znoyes@gmail.com<\/a><!-- ws:end:WikiTextUrlEmailRule:7 --><br \/>\n--Zach","replies":[]}